smartbotsol/__init__.py
smartbotsol/singleton.py
smartbotsol/smartbotsol.py
smartbotsol/caches/__init__.py
smartbotsol/caches/dictcache.py
smartbotsol/core/__init__.py
smartbotsol/core/cache.py
smartbotsol/core/filter.py
smartbotsol/core/state.py
smartbotsol/core/statemachine.py
smartbotsol/core/trigger.py
smartbotsol/core/user.py
smartbotsol/telegram/__init__.py
smartbotsol/telegram/handeledfsm.py
smartbotsol/telegram/telegramtrigger.py
smartbotsol/telegram/handlers/__init__.py
smartbotsol/telegram/handlers/fsmhandler.py
smartbotsol/telegram/utils/__init__.py
smartbotsol/telegram/utils/helpers.py
smartbotsol/telegram/utils/keys.py
smartbotsol-1.0.1.dist-info/DESCRIPTION.rst
smartbotsol-1.0.1.dist-info/METADATA
smartbotsol-1.0.1.dist-info/RECORD
smartbotsol-1.0.1.dist-info/WHEEL
smartbotsol-1.0.1.dist-info/metadata.json
smartbotsol-1.0.1.dist-info/top_level.txt
