Metadata-Version: 2.0
Name: smartbotsol
Version: 1.0.1
Summary: smart conversation bots package
Home-page: https://github.com/dqunbp/smartbotsol
Author: Tigran Grigoryan
Author-email: dqunbp@gmail.com
License: MIT license
Keywords: smartbotsol
Platform: UNKNOWN
Classifier: Development Status :: 2 - Pre-Alpha
Classifier: Intended Audience :: Developers
Classifier: License :: OSI Approved :: MIT License
Classifier: Natural Language :: English
Classifier: Programming Language :: Python :: 2
Classifier: Programming Language :: Python :: 2.6
Classifier: Programming Language :: Python :: 2.7
Classifier: Programming Language :: Python :: 3
Classifier: Programming Language :: Python :: 3.3
Classifier: Programming Language :: Python :: 3.4
Classifier: Programming Language :: Python :: 3.5
Requires-Dist: python-telegram-bot (==7.0.1)
Requires-Dist: dill
